setup.py
simple_requests/__init__.py
simple_requests/compat.py
simple_requests/monkey.py
simple_requests/simple_requests.py
simple_requests/strategy.py
simple_requests.egg-info/PKG-INFO
simple_requests.egg-info/SOURCES.txt
simple_requests.egg-info/dependency_links.txt
simple_requests.egg-info/not-zip-safe
simple_requests.egg-info/requires.txt
simple_requests.egg-info/top_level.txt