Metadata-Version: 1.1
Name: simple-requests
Version: 1.1.1
Summary: Asynchronous requests in Python without thinking about it.
Home-page: https://github.com/ctheiss/simple-requests
Author: Corey Theiss
Author-email: corey@exploringsolutions.com
License: MIT
Platform: any
Classifier: Environment :: Web Environment
Classifier: Intended Audience :: Developers
Classifier: License :: OSI Approved :: MIT License
Classifier: Operating System :: OS Independent
Classifier: Programming Language :: Python
Classifier: Topic :: Internet :: WWW/HTTP :: Dynamic Content
Classifier: Topic :: Software Development :: Libraries :: Python Modules
